dbt_swap/__init__.py
dbt_swap/cli/__init__.py
dbt_swap/cli/common.py
dbt_swap/cli/get_manifest.py
dbt_swap/cli/main.py
dbt_swap/cli/smart_build.py
dbt_swap/core/__init__.py
dbt_swap/core/smart_builder.py
dbt_swap/utils/__init__.py
dbt_swap/utils/logging.py
dbt_swap/utils/run_dbt.py
dbt_swap-1.6.10.dist-info/WHEEL
dbt_swap-1.6.10.dist-info/entry_points.txt
dbt_swap-1.6.10.dist-info/METADATA
dbt_swap-1.6.10.dist-info/RECORD
