Metadata-Version: 2.3
Name: dbt-swap
Version: 1.6.10
Summary: A cli tool that adds a number of custom dbt commands.
Author: Tobias Cadee
Author-email: Tobias Cadee <tobias.cadee@ticketswap.com>
Requires-Dist: boto3>=1.40.56
Requires-Dist: sqlglot>=27
Requires-Dist: typer>=0.19.2
Requires-Python: >=3.11
